pyconfiger/__init__.py
pyconfiger-0.1.3.dist-info/LICENSE.md
pyconfiger-0.1.3.dist-info/METADATA
pyconfiger-0.1.3.dist-info/WHEEL
pyconfiger-0.1.3.dist-info/top_level.txt
pyconfiger-0.1.3.dist-info/RECORD
