Metadata-Version: 2.1
Name: pyconfiger
Version: 0.1.3
Summary: A simple python module to handle your project settings
Home-page: https://github.com/Randomneo/pyconfiger
Author: Rostyslav Misiura
Author-email: rostislav9999@gmail.com
Maintainer: Rostyslav Misiura
Maintainer-email: rostislav9999@gmail.com
License: GNU Affero General Public License, version 3
Classifier: Intended Audience :: Developers
Classifier: License :: OSI Approved :: GNU General Public License v3 (GPLv3)
Classifier: Operating System :: OS Independent
Classifier: Programming Language :: Python :: 3
Classifier: Programming Language :: Python :: 3.9
License-File: LICENSE.md
